LICENSE
MANIFEST.in
README.md
setup.py
django_entur_data.egg-info/PKG-INFO
django_entur_data.egg-info/SOURCES.txt
django_entur_data.egg-info/dependency_links.txt
django_entur_data.egg-info/requires.txt
django_entur_data.egg-info/top_level.txt
rutedata/__init__.py
rutedata/admin.py
rutedata/apps.py
rutedata/models.py
rutedata/urls.py
rutedata/views.py
rutedata/load_xml/LinePassingHelper.py
rutedata/load_xml/LoadLines.py
rutedata/load_xml/LoadStopPoints.py
rutedata/load_xml/LoadStops.py
rutedata/load_xml/__init__.py
rutedata/load_xml/line_helper.py
rutedata/load_xml/load_xml.py
rutedata/management/__init.py
rutedata/management/commands/__init.py
rutedata/management/commands/line_colors.py
rutedata/management/commands/load_lines.py
rutedata/management/commands/load_point_on_route.py
rutedata/management/commands/load_route.py
rutedata/management/commands/load_stop_points.py
rutedata/management/commands/load_stops.py
rutedata/migrations/0001_initial.py
rutedata/migrations/0002_passingtime_line.py
rutedata/migrations/0003_lat_lon_null.py
rutedata/migrations/0004_quay_fields.py
rutedata/migrations/__init__.py
rutedata/templates/rutedata/lines.html
rutedata/templates/rutedata/routes.html
rutedata/templates/rutedata/service_journey.html
rutedata/templates/rutedata/stops_kml.html
tests/__init__.py
tests/test_lines.py
tests/test_load_stops.py
tests/test_settings.py